<errors>

  <error id="msyn-wrong_case" legacyid="-1">
    <header>
      <title xml:lang="en">Wrong case</title>
    </header>
    <body>
      <description xml:lang="en">The word "$1" is in the wrong case.</description>
    </body>
  </error>

  <error id="orth-prop" legacyid="-1">
    <header>
      <title xml:lang="en">Capitalisation of proper nouns</title>
    </header>
    <body>
      <description xml:lang="en">The proper noun "$1" should begin with a capital letter.</description>
    </body>
  </error>

</errors>
